phpgp/__init__.py
phpgp/cli.py
phpgp/server.py
phpgp/utils.py
phpgp-1.1.0.dist-info/licenses/LICENSE
phpgp-1.1.0.dist-info/METADATA
phpgp-1.1.0.dist-info/WHEEL
phpgp-1.1.0.dist-info/entry_points.txt
phpgp-1.1.0.dist-info/top_level.txt
phpgp-1.1.0.dist-info/RECORD
