Metadata-Version: 2.4
Name: phpgp
Version: 1.1.0
Summary: phPGP - tool to store your PGP keys on the physical storage (USB, flash drive etc.)
Home-page: https://github.com/zabojeb/phpgp
Author: zabojeb
Author-email: zabojeb@bk.ru
Project-URL: Bug Tracker, https://github.com/zabojeb/phpgp/issues
Classifier: Programming Language :: Python :: 3
Classifier: Operating System :: OS Independent
Requires-Python: >=3.7
License-File: LICENSE
Requires-Dist: pgpy13
Requires-Dist: psutil
Requires-Dist: prompt_toolkit
Requires-Dist: click
Requires-Dist: cryptography
Requires-Dist: python-gnupg
Requires-Dist: keyring
Provides-Extra: dev
Requires-Dist: pytest; extra == "dev"
Requires-Dist: black; extra == "dev"
Dynamic: license-file
